xecd_rates/Xecd.py
xecd_rates/__init__.py
xecd_rates-1.0.3.dist-info/LICENCE
xecd_rates-1.0.3.dist-info/METADATA
xecd_rates-1.0.3.dist-info/WHEEL
xecd_rates-1.0.3.dist-info/top_level.txt
xecd_rates-1.0.3.dist-info/zip-safe
xecd_rates-1.0.3.dist-info/RECORD
