Metadata-Version: 2.1
Name: xecd-rates
Version: 1.0.3
Summary: Xecd Rates Python: Free currency  rates converter
Home-page: https://github.com/doguskidik/xecd-rates-python
Author: Doğuş KIDIK
Author-email: dogus.kidik@gmail.com
License: MIT
Platform: UNKNOWN
Classifier: Programming Language :: Python :: 3
Classifier: Programming Language :: Python :: 3.5
Classifier: Programming Language :: Python :: 3.6
Classifier: Programming Language :: Python :: 3.7
Classifier: Programming Language :: Python :: 3.8
Classifier: License :: OSI Approved :: MIT License
Classifier: Operating System :: OS Independent
Classifier: Development Status :: 4 - Beta
Requires-Dist: requests
Requires-Dist: lxml
